pybs/.DS_Store
pybs/__init__.py
pybs/console/__init__.py
pybs/console/console.py
pybs/console/local/__init__.py
pybs/console/local/commands.py
pybs/console/remote/README.md
pybs/console/remote/__init__.py
pybs/console/remote/code.py
pybs/console/remote/commands.py
pybs/console/tabcomplete.py
pybs/console/ui/__init__.py
pybs/constants/__init__.py
pybs/server/__init__.py
pythonpbs-0.1.5.dist-info/LICENSE
pythonpbs-0.1.5.dist-info/METADATA
pythonpbs-0.1.5.dist-info/WHEEL
pythonpbs-0.1.5.dist-info/entry_points.txt
pythonpbs-0.1.5.dist-info/RECORD
