Metadata-Version: 2.3
Name: pythonpbs
Version: 0.1.5
Summary: Python-based PBS job submission
License: Apache-2.0
Author: Kâmuran İmran
Author-email: c.mcmenamie@unsw.edu.au
Requires-Python: >=3.9,<4.0
Classifier: License :: OSI Approved :: Apache Software License
Classifier: Programming Language :: Python :: 3
Classifier: Programming Language :: Python :: 3.9
Classifier: Programming Language :: Python :: 3.10
Classifier: Programming Language :: Python :: 3.11
Classifier: Programming Language :: Python :: 3.12
Classifier: Programming Language :: Python :: 3.13
Requires-Dist: black[jupyter] (>=25.1.0,<26.0.0)
Requires-Dist: cleo (>=2.1.0,<3.0.0)
Requires-Dist: click (>=8.1.8,<9.0.0)
Requires-Dist: loguru (>=0.7.3,<0.8.0)
Requires-Dist: platformdirs (>=4.3.6,<5.0.0)
Requires-Dist: rich (>=13.9.4,<14.0.0)
Requires-Dist: setuptools (>=75.8.2,<76.0.0)
Requires-Dist: sshconf (>=0.2.7,<0.3.0)
Requires-Dist: tqdm (>=4.67.1,<5.0.0)
